json_profiler/__init__.py
json_profiler/core.py
json_profiler-0.1.0.dist-info/METADATA
json_profiler-0.1.0.dist-info/WHEEL
json_profiler-0.1.0.dist-info/top_level.txt
json_profiler-0.1.0.dist-info/RECORD
