Metadata-Version: 2.4
Name: json-profiler
Version: 0.1.0
Summary: A tool for exploring and analyzing JSON structure with aggregated statistics
Home-page: https://github.com/yourusername/json-explorer
Author: Edwin Zhang
Author-email: Edwin Zhang <edwin.zhang@slopeful.com>
License: MIT
Project-URL: Homepage, https://github.com/yourusername/json-explorer
Project-URL: Bug Tracker, https://github.com/yourusername/json-explorer/issues
Classifier: Development Status :: 3 - Alpha
Classifier: Intended Audience :: Developers
Classifier: License :: OSI Approved :: MIT License
Classifier: Operating System :: OS Independent
Classifier: Programming Language :: Python :: 3
Classifier: Programming Language :: Python :: 3.7
Classifier: Programming Language :: Python :: 3.8
Classifier: Programming Language :: Python :: 3.9
Classifier: Programming Language :: Python :: 3.10
Classifier: Programming Language :: Python :: 3.11
Requires-Python: >=3.7
Dynamic: author
Dynamic: home-page
Dynamic: requires-python
